datacreator/__init__.py
datacreator/datacreator.py
datacreator-0.0.1.dist-info/LICENSE.rtf
datacreator-0.0.1.dist-info/METADATA
datacreator-0.0.1.dist-info/WHEEL
datacreator-0.0.1.dist-info/top_level.txt
datacreator-0.0.1.dist-info/RECORD
