Metadata-Version: 2.1
Name: datacreator
Version: 0.0.1
Summary: A synthetic data creator package
Home-page: https://github.com/fau-syn-data/synthetic-data.git
Author: BACS_group1
Author-email: fausyndata@gmail.com
License: UNKNOWN
Platform: UNKNOWN
Classifier: Programming Language :: Python :: 3
Classifier: License :: OSI Approved :: MIT License
Classifier: Operating System :: OS Independent
